cs/app/osx/spaces.py
cs_app_osx_spaces-20250306.dist-info/entry_points.txt
cs_app_osx_spaces-20250306.dist-info/WHEEL
cs_app_osx_spaces-20250306.dist-info/METADATA
cs_app_osx_spaces-20250306.dist-info/RECORD
