Metadata-Version: 2.4
Name: cs-app-osx-spaces
Version: 20250306
Summary: Access to the MacOS X display spaces.
Keywords: python3
Author-email: Cameron Simpson <cs@cskk.id.au>
Classifier: Development Status :: 4 - Beta
Classifier: Environment :: MacOS X
Classifier: Intended Audience :: End Users/Desktop
Classifier: Programming Language :: Python :: 3
Classifier: Topic :: Desktop Environment
Classifier: Operating System :: OS Independent
Classifier: License :: OSI Approved :: GNU General Public License v3 or later (GPLv3+)
Requires-Dist: cs.app.osx.misc>=20240622.1
Requires-Dist: cs.app.osx.objc>=20240622
Requires-Dist: cs.cmdutils>=20250306
Requires-Dist: cs.context>=20250306
Requires-Dist: cs.delta>=20240622
Requires-Dist: cs.fs>=20241122
Requires-Dist: cs.lex>=20250103
Requires-Dist: cs.pfx>=20241208
Requires-Dist: pyobjc
Requires-Dist: typeguard
Project-URL: MonoRepo Commits, https://bitbucket.org/cameron_simpson/css/commits/branch/main
Project-URL: Monorepo Git Mirror, https://github.com/cameron-simpson/css
Project-URL: Monorepo Hg/Mercurial Mirror, https://hg.sr.ht/~cameron-simpson/css
Project-URL: Source, https://github.com/cameron-simpson/css/blob/main/lib/python/cs/app/osx/spaces.py
